app_store_connect_api_client/__init__.py
app_store_connect_api_client/client.py
app_store_connect_api_client/resources/__init__.py
app_store_connect_api_client/resources/base.py
app_store_connect_api_client/utils.py
app_store_connect_api_client-0.1.0.dist-info/WHEEL
app_store_connect_api_client-0.1.0.dist-info/METADATA
app_store_connect_api_client-0.1.0.dist-info/RECORD
